botify/__init__.py
botify/core/__init__.py
botify/core/botify.py
botify/core/config.py
botify/core/default.py
botify/core/media.py
botify/core/storage.py
botify/db/__init__.py
botify/db/db.py
botify/db/model.py
botify/db/query.py
botify/engine/__init__.py
botify/engine/button.py
botify/engine/engine.py
botify/utils/__init__.py
botify/utils/container.py
botify/utils/logger.py
botify_telegram-0.0.1.dist-info/LICENSE
botify_telegram-0.0.1.dist-info/METADATA
botify_telegram-0.0.1.dist-info/WHEEL
botify_telegram-0.0.1.dist-info/top_level.txt
botify_telegram-0.0.1.dist-info/RECORD
