Metadata-Version: 2.1
Name: botify-telegram
Version: 0.0.1
Summary: Modern solution for telegram bots development
Home-page: https://github.com/dmitriypaulov/botify
Author: Dmitriy Paulov
Author-email: dmitriy.paulov@gmail.com
License: UNKNOWN
Project-URL: Bug Tracker, https://github.com/dmitriypaulov/botify/issues
Platform: UNKNOWN
Classifier: Programming Language :: Python :: 3
Classifier: License :: OSI Approved :: MIT License
Classifier: Operating System :: OS Independent
Requires-Python: >=3.7
